HDL/Design/ESDES/ESDES.v
module SDES(input [7:0] nonce, input [9:0] key,output [7:0] rn);
  reg [8:0]nonceinv, IP,EP_1,key_1,key_2,epxork_1,EP_2,epxork_2,IP_inv,finalsum;
  reg [9:0] keyinv;
  reg [3:0] nonce_r, nonce_l, aftersbox_1,aftersbox_2, P4,round2inp,P4_2,noncerxorp4;
  reg [1:0] s0_1,s1_1,s0_2,s1_2;
  always @ (*) begin
    keyinv = ~key;
    key_1 = {keyinv[9],keyinv[3],keyinv[1],keyinv[6],keyinv[2],keyinv[7],keyinv[0],keyinv[4]};
    key_2 = {keyinv[2],keyinv[7],keyinv[4],keyinv[5],keyinv[0],keyinv[8],keyinv[1],keyinv[9]};
    nonceinv = ~nonce;
    IP = {nonceinv[6], nonceinv[2], nonceinv[5], nonceinv[7],nonceinv[4], nonceinv[0], nonceinv[3], nonceinv[1]};
    nonce_r = IP[3:0];
    nonce_l = IP[7:4];
    EP_1 =  {nonce_r[0], nonce_r[3], nonce_r[2], nonce_r[1], nonce_r[2], nonce_r[1], nonce_r[0], nonce_r[3]};
    epxork_1 = key_1 ^ EP_1;
    // S0 box for round1         
    case (epxork_1[7:4])     
      4'b0000	:  s0_1 = 2'b01;
      4'b0001	:  s0_1 = 2'b11;
      4'b0010	:  s0_1 = 2'b00;
      4'b0011	:  s0_1 = 2'b10;
      4'b0100	:  s0_1 = 2'b11;
      4'b0101	:  s0_1 = 2'b01;
      4'b0110	:  s0_1 = 2'b10;
      4'b0111	:  s0_1 = 2'b00;
      4'b1000	:  s0_1 = 2'b00;
      4'b1001	:  s0_1 = 2'b11;
      4'b1010	:  s0_1 = 2'b10;
      4'b1011	:  s0_1 = 2'b01;
      4'b1100	:  s0_1 = 2'b01;
      4'b1101	:  s0_1 = 2'b11;
      4'b1110	:  s0_1 = 2'b11;
      4'b1111	:  s0_1 = 2'b10;
     endcase 
     // S1 box for round1  
     case (epxork_1[3:0])
     
      4'b0000 : s1_1 = 2'b00;
      4'b0001 : s1_1 = 2'b10;
      4'b0010 : s1_1 = 2'b01;
      4'b0011 : s1_1 = 2'b00;
      4'b0100 : s1_1 = 2'b10;
      4'b0101 : s1_1 = 2'b01;
      4'b0110 : s1_1 = 2'b11;
      4'b0111 : s1_1 = 2'b11;
      4'b1000 : s1_1 = 2'b11;
      4'b1001 : s1_1 = 2'b10;
      4'b1010 : s1_1 = 2'b00;
      4'b1011 : s1_1 = 2'b01;
      4'b1100 : s1_1 = 2'b01;
      4'b1101 : s1_1 = 2'b00;
      4'b1110 : s1_1 = 2'b00;
      4'b1111 : s1_1 = 2'b11;
		endcase 
    aftersbox_1 = {s0_1,s1_1};
    P4 = {aftersbox_1[2],
          aftersbox_1[0],
          aftersbox_1[1],
          aftersbox_1[3]}; 
    round2inp = nonce_l ^ P4;
    // round 2
    EP_2 =  {round2inp[0],
             round2inp[3],
             round2inp[2],
             round2inp[1],
             round2inp[2],
             round2inp[1],
             round2inp[0],
             round2inp[3]};
    epxork_2 = EP_2 ^ key_2;
        // S0 box for round2         
    case (epxork_2[7:4])     
      4'b0000	:  s0_2 = 2'b01;
      4'b0001	:  s0_2 = 2'b11;
      4'b0010	:  s0_2 = 2'b00;
      4'b0011	:  s0_2 = 2'b10;
      4'b0100	:  s0_2 = 2'b11;
      4'b0101	:  s0_2 = 2'b01;
      4'b0110	:  s0_2 = 2'b10;
      4'b0111	:  s0_2 = 2'b00;
      4'b1000	:  s0_2 = 2'b00;
      4'b1001	:  s0_2 = 2'b11;
      4'b1010	:  s0_2 = 2'b10;
      4'b1011	:  s0_2 = 2'b01;
      4'b1100	:  s0_2 = 2'b01;
      4'b1101	:  s0_2 = 2'b11;
      4'b1110	:  s0_2 = 2'b11;
      4'b1111	:  s0_2 = 2'b10;
     endcase 
     // S1 box for round2 
    case (epxork_2[3:0])
     
      4'b0000 : s1_2 = 2'b00;
      4'b0001 : s1_2 = 2'b10;
      4'b0010 : s1_2 = 2'b01;
      4'b0011 : s1_2 = 2'b00;
      4'b0100 : s1_2 = 2'b10;
      4'b0101 : s1_2 = 2'b01;
      4'b0110 : s1_2 = 2'b11;
      4'b0111 : s1_2 = 2'b11;
      4'b1000 : s1_2 = 2'b11;
      4'b1001 : s1_2 = 2'b10;
      4'b1010 : s1_2 = 2'b00;
      4'b1011 : s1_2 = 2'b01;
      4'b1100 : s1_2 = 2'b01;
      4'b1101 : s1_2 = 2'b00;
      4'b1110 : s1_2 = 2'b00;
      4'b1111 : s1_2 = 2'b11;
		endcase 
    aftersbox_2 = {s0_2,s1_2};
    P4_2 = {aftersbox_2[2],
            aftersbox_2[0],
            aftersbox_2[1],
            aftersbox_2[3]}; 
    noncerxorp4 = nonce_r ^ P4_2;
    finalsum = {noncerxorp4,round2inp} ;
    IP_inv ={finalsum[4],
             finalsum[7],
             finalsum[5],
             finalsum[3],
             finalsum[1],
             finalsum[6],
             finalsum[0],
             finalsum[2]};
 
    
    
    
   
  end
  assign    rn = ~IP_inv;
endmodule

HDL/Testbench/ESDES/testbench.sv
module testbench();

  reg [7:0] nonce;
  reg [9:0] key;
  wire [7:0] rn;
  reg mismatch;

  SDES dut (
    .nonce(nonce),
    .key(key),
    .rn(rn)
  );
    initial begin
    $dumpfile("dump.vcd"); 
    $dumpvars(1);
    
  end

  initial begin
    mismatch =0;
  
  	// false test 
    nonce = 8'h0a;
    key = 10'h010;
    #10;
    if (rn !== 8'hf0) begin
      $display("Test failed: Output mismatch!");
      mismatch = 1;
    end
    else begin
      mismatch = 0;
    end
  
  
  
    // Test 1 
    nonce = 8'h00;
    key = 10'h000;
    #10;
    if (rn !== 8'hf0) begin
      $display("Test 1 failed: Output mismatch!");
      mismatch = 1;
    end
    else begin
       mismatch = 0;
    end

    // Test 2 
    nonce = 8'hff;
    key = 10'h3ff;
    #10;
    if (rn !== 8'h0f) begin
      $display("Test 2 failed: Output mismatch!");
      mismatch = 1;
    end
    else begin
       mismatch = 0;
    end
    
    // test 3
     nonce = 8'h11;
    key = 10'h001;
    #10;
    if (rn !== 8'hc3) begin
      $display("Test 3 failed: Output mismatch!");
      mismatch = 1;
    end
    else begin
        mismatch = 0;
    end
    
    // test 4
     nonce = 8'hb1;
    key = 10'h102;
    #10;
    if (rn !== 8'hb0) begin
      $display("Test 4 failed: Output mismatch!");
      mismatch = 1;
    end
    else begin
       mismatch = 0;
    end
    
    // test 5
     nonce = 8'hb1;
    key = 10'h1a2;
    #10;
    if (rn !== 8'h1c) begin
      $display("Test 5 failed: Output mismatch!");
      mismatch = 1;
    end
    else begin
        mismatch = 0;
    end
    
    // test 6
     nonce = 8'hd2;
    key = 10'h1a2;
    #10;
    if (rn !== 8'h49) begin
      $display("Test 6 failed: Output mismatch!");
      mismatch = 1;
    end
    else begin
        mismatch = 0;
    end
    
    // test 7
     nonce = 8'hd2;
    key = 10'h1b2;
    #10;
    if (rn !== 8'h09) begin
      $display("Test 7 failed: Output mismatch!");
      mismatch = 1;
    end
    else begin
        mismatch = 0;
    end
    
    // test 8
     nonce = 8'he4;
    key = 10'h2c2;
    #10;
    if (rn !== 8'he3) begin
      $display("Test 8 failed: Output mismatch!");
      mismatch = 1;
    end
    else begin
       mismatch = 0;
    end
    
    // test 9
     nonce = 8'hf5;
    key = 10'h0c5;
    #10;
    if (rn !== 8'h12) begin
      $display("Test 9 failed: Output mismatch!");
      mismatch = 1;
    end
    else begin
       mismatch = 0;
    end
    
    // test 10
     nonce = 8'h18;
    key = 10'h0d5;
    #10;
    if (rn !== 8'h76) begin
      $display("Test 10 failed: Output mismatch!");
      mismatch = 1;
    end
    else begin
        mismatch = 0;
    end
    
  end

endmodule

HDL/Dump/ESDES/dump.vcd
$date
	Fri Mar 17 10:44:38 2023
$end
$version
	Icarus Verilog
$end
$timescale
	1s
$end
$scope module testbench $end
$var wire 8 ! rn [7:0] $end
$var reg 10 " key [9:0] $end
$var reg 1 # mismatch $end
$var reg 8 $ nonce [7:0] $end
$upscope $end
$enddefinitions $end
#0
$dumpvars
b1010 $
0#
b10000 "
b1011111 !
$end
#10
b11110000 !
b0 "
b0 $
1#
#20
b1111 !
b1111111111 "
b11111111 $
0#
#30
b11000011 !
b1 "
b10001 $
#40
b10110000 !
b100000010 "
b10110001 $
#50
b11100 !
b110100010 "
#60
b1001001 !
b11010010 $
#70
b1001 !
b110110010 "
#80
b11100011 !
b1011000010 "
b11100100 $
#90
b10010 !
b11000101 "
b11110101 $
#100
b1110110 !
b11010101 "
b11000 $
