HDL/Design/ESDES/ESDES.v
module SDES(input [7:0] nonce, input [9:0] key,output [7:0] rn);
  reg [8:0]nonceinv, IP,EP_1,key_1,key_2,epxork_1,EP_2,epxork_2,IP_inv,finalsum;
  reg [9:0] keyinv;
  reg [3:0] nonce_r, nonce_l, aftersbox_1,aftersbox_2, P4,round2inp,P4_2,noncerxorp4;
  reg [1:0] s0_1,s1_1,s0_2,s1_2;
  always @ (*) begin
    keyinv = ~key;
    key_1 = {keyinv[9],keyinv[3],keyinv[1],keyinv[6],keyinv[2],keyinv[7],keyinv[0],keyinv[4]};
    key_2 = {keyinv[2],keyinv[7],keyinv[4],keyinv[5],keyinv[0],keyinv[8],keyinv[1],keyinv[9]};
    nonceinv = ~nonce;
    IP = {nonceinv[6], nonceinv[2], nonceinv[5], nonceinv[7],nonceinv[4], nonceinv[0], nonceinv[3], nonceinv[1]};
    nonce_r = IP[3:0];
    nonce_l = IP[7:4];
    EP_1 =  {nonce_r[0], nonce_r[3], nonce_r[2], nonce_r[1], nonce_r[2], nonce_r[1], nonce_r[0], nonce_r[3]};
    epxork_1 = key_1 ^ EP_1;
    // S0 box for round1         
    case (epxork_1[7:4])     
      4'b0000	:  s0_1 = 2'b01;
      4'b0001	:  s0_1 = 2'b11;
      4'b0010	:  s0_1 = 2'b00;
      4'b0011	:  s0_1 = 2'b10;
      4'b0100	:  s0_1 = 2'b11;
      4'b0101	:  s0_1 = 2'b01;
      4'b0110	:  s0_1 = 2'b10;
      4'b0111	:  s0_1 = 2'b00;
      4'b1000	:  s0_1 = 2'b00;
      4'b1001	:  s0_1 = 2'b11;
      4'b1010	:  s0_1 = 2'b10;
      4'b1011	:  s0_1 = 2'b01;
      4'b1100	:  s0_1 = 2'b01;
      4'b1101	:  s0_1 = 2'b11;
      4'b1110	:  s0_1 = 2'b11;
      4'b1111	:  s0_1 = 2'b10;
     endcase 
     // S1 box for round1  
     case (epxork_1[3:0])
     
      4'b0000 : s1_1 = 2'b00;
      4'b0001 : s1_1 = 2'b10;
      4'b0010 : s1_1 = 2'b01;
      4'b0011 : s1_1 = 2'b00;
      4'b0100 : s1_1 = 2'b10;
      4'b0101 : s1_1 = 2'b01;
      4'b0110 : s1_1 = 2'b11;
      4'b0111 : s1_1 = 2'b11;
      4'b1000 : s1_1 = 2'b11;
      4'b1001 : s1_1 = 2'b10;
      4'b1010 : s1_1 = 2'b00;
      4'b1011 : s1_1 = 2'b01;
      4'b1100 : s1_1 = 2'b01;
      4'b1101 : s1_1 = 2'b00;
      4'b1110 : s1_1 = 2'b00;
      4'b1111 : s1_1 = 2'b11;
		endcase 
    aftersbox_1 = {s0_1,s1_1};
    P4 = {aftersbox_1[2],
          aftersbox_1[0],
          aftersbox_1[1],
          aftersbox_1[3]}; 
    round2inp = nonce_l ^ P4;
    // round 2
    EP_2 =  {round2inp[0],
             round2inp[3],
             round2inp[2],
             round2inp[1],
             round2inp[2],
             round2inp[1],
             round2inp[0],
             round2inp[3]};
    epxork_2 = EP_2 ^ key_2;
        // S0 box for round2         
    case (epxork_2[7:4])     
      4'b0000	:  s0_2 = 2'b01;
      4'b0001	:  s0_2 = 2'b11;
      4'b0010	:  s0_2 = 2'b00;
      4'b0011	:  s0_2 = 2'b10;
      4'b0100	:  s0_2 = 2'b11;
      4'b0101	:  s0_2 = 2'b01;
      4'b0110	:  s0_2 = 2'b10;
      4'b0111	:  s0_2 = 2'b00;
      4'b1000	:  s0_2 = 2'b00;
      4'b1001	:  s0_2 = 2'b11;
      4'b1010	:  s0_2 = 2'b10;
      4'b1011	:  s0_2 = 2'b01;
      4'b1100	:  s0_2 = 2'b01;
      4'b1101	:  s0_2 = 2'b11;
      4'b1110	:  s0_2 = 2'b11;
      4'b1111	:  s0_2 = 2'b10;
     endcase 
     // S1 box for round2 
    case (epxork_2[3:0])
     
      4'b0000 : s1_2 = 2'b00;
      4'b0001 : s1_2 = 2'b10;
      4'b0010 : s1_2 = 2'b01;
      4'b0011 : s1_2 = 2'b00;
      4'b0100 : s1_2 = 2'b10;
      4'b0101 : s1_2 = 2'b01;
      4'b0110 : s1_2 = 2'b11;
      4'b0111 : s1_2 = 2'b11;
      4'b1000 : s1_2 = 2'b11;
      4'b1001 : s1_2 = 2'b10;
      4'b1010 : s1_2 = 2'b00;
      4'b1011 : s1_2 = 2'b01;
      4'b1100 : s1_2 = 2'b01;
      4'b1101 : s1_2 = 2'b00;
      4'b1110 : s1_2 = 2'b00;
      4'b1111 : s1_2 = 2'b11;
		endcase 
    aftersbox_2 = {s0_2,s1_2};
    P4_2 = {aftersbox_2[2],
            aftersbox_2[0],
            aftersbox_2[1],
            aftersbox_2[3]}; 
    noncerxorp4 = nonce_r ^ P4_2;
    finalsum = {noncerxorp4,round2inp} ;
    IP_inv ={finalsum[4],
             finalsum[7],
             finalsum[5],
             finalsum[3],
             finalsum[1],
             finalsum[6],
             finalsum[0],
             finalsum[2]};
 
    
    
    
   
  end
  assign    rn = ~IP_inv;
endmodule

HDL/Design/StreamESDES/StreamESDES.v
// async reset 
module circuit(
  input clk,
  input rst,
  input [7:0] nonce,
  input [7:0] plaintext,
  input [9:0] key,
  output reg [7:0] ciphertext
);

  reg [7:0] nonce_reg, plaintext_reg, plaintext_reg_delayed, sdes_output_reg;
  wire [7:0] sdes_output_wire;
  
  SDES sdes_inst(nonce_reg, key, sdes_output_wire);
  assign ciphertext = sdes_output_reg ^ plaintext_reg_delayed;
  
  always @(posedge clk, posedge rst) begin
    if (rst) begin
      nonce_reg <= 8'b0;
      plaintext_reg <= 8'b0;
      plaintext_reg_delayed <= 8'b0;
      sdes_output_reg <= 8'b0;
    end else begin
      plaintext_reg <= plaintext;
      plaintext_reg_delayed <= plaintext_reg;
      sdes_output_reg <= sdes_output_wire;
      
      if (|sdes_output_reg == 1'b1) begin
        nonce_reg <= sdes_output_reg;
      end else begin
        nonce_reg <= nonce;
      end
    end
  end
  
endmodule


// //Syncreset 
// module circuit(
//   input clk,
//   input rst,
//   input [7:0] nonce,
//   input [7:0] plaintext,
//   input [9:0] key,
//   output reg [7:0] ciphertext
// );

//   reg [7:0] nonce_reg, plaintext_reg, plaintext_reg_delayed, sdes_output_reg;
//   wire [7:0] sdes_output_wire;
  
//   SDES sdes_inst(nonce_reg, key, sdes_output_wire);
//   assign ciphertext = sdes_output_reg ^ plaintext_reg_delayed;
  
//   always @(posedge clk) begin
//     if (rst) begin
//       nonce_reg <= 8'b0;
//       plaintext_reg <= 8'b0;
//       plaintext_reg_delayed <= 8'b0;
//       sdes_output_reg <= 8'b0;
//     end else begin
//       plaintext_reg <= plaintext;
//       plaintext_reg_delayed <= plaintext_reg;
//       sdes_output_reg <= sdes_output_wire;
      
//       if (|sdes_output_reg == 1'b1) begin
//         nonce_reg <= sdes_output_reg;
//       end else begin
//         nonce_reg <= nonce;
//       end
//     end
//   end
  
// endmodule

HDL/Testbench/StreamEsdes/testbench.v
module testbench;

  // Declare inputs and outputs
  reg clk, rst; 
  reg [7:0] nonce, plaintext;
  reg [9:0] key;
  wire [7:0] ciphertext;

  // Instantiate the module under test
  circuit inst(
    .clk(clk),
    .rst(rst),
    .nonce(nonce),
    .plaintext(plaintext),
    .key(key),
    .ciphertext(ciphertext)
  );
  
  // Generate clock signal
  always #1 clk = ~clk;

  // Initialize inputs
  initial begin
    // Dump waveform to VCD file
    $dumpfile("streamesdes.vcd");
    $dumpvars();
    
    // Set initial input values
    clk = 0;
    nonce = 8'b00001000;
    plaintext = 8'b00000000;
    key = 10'b0000000100;
    rst = 1;
    #5rst = 0;
	#10 rst = 1;
    #1 nonce = 8'b00010000;
    #3rst = 0;
    #20 rst = 1;
    #50 $finish;
  end 
endmodule

HDL/Testbench/StreamEsdes/streamesdes.vcd
$date
	Fri Mar 31 12:06:53 2023
$end
$version
	Icarus Verilog
$end
$timescale
	1s
$end
$scope module testbench $end
$var wire 8 ! ciphertext [7:0] $end
$var reg 1 " clk $end
$var reg 10 # key [9:0] $end
$var reg 8 $ nonce [7:0] $end
$var reg 8 % plaintext [7:0] $end
$var reg 1 & rst $end
$scope module inst $end
$var wire 8 ' ciphertext [7:0] $end
$var wire 1 " clk $end
$var wire 10 ( key [9:0] $end
$var wire 8 ) nonce [7:0] $end
$var wire 8 * plaintext [7:0] $end
$var wire 1 & rst $end
$var wire 8 + sdes_output_wire [7:0] $end
$var reg 8 , nonce_reg [7:0] $end
$var reg 8 - plaintext_reg [7:0] $end
$var reg 8 . plaintext_reg_delayed [7:0] $end
$var reg 8 / sdes_output_reg [7:0] $end
$scope module sdes_inst $end
$var wire 10 0 key [9:0] $end
$var wire 8 1 nonce [7:0] $end
$var wire 8 2 rn [7:0] $end
$var reg 9 3 EP_1 [8:0] $end
$var reg 9 4 EP_2 [8:0] $end
$var reg 9 5 IP [8:0] $end
$var reg 9 6 IP_inv [8:0] $end
$var reg 4 7 P4 [3:0] $end
$var reg 4 8 P4_2 [3:0] $end
$var reg 4 9 aftersbox_1 [3:0] $end
$var reg 4 : aftersbox_2 [3:0] $end
$var reg 9 ; epxork_1 [8:0] $end
$var reg 9 < epxork_2 [8:0] $end
$var reg 9 = finalsum [8:0] $end
$var reg 9 > key_1 [8:0] $end
$var reg 9 ? key_2 [8:0] $end
$var reg 10 @ keyinv [9:0] $end
$var reg 4 A nonce_l [3:0] $end
$var reg 4 B nonce_r [3:0] $end
$var reg 9 C nonceinv [8:0] $end
$var reg 4 D noncerxorp4 [3:0] $end
$var reg 4 E round2inp [3:0] $end
$var reg 2 F s0_1 [1:0] $end
$var reg 2 G s0_2 [1:0] $end
$var reg 2 H s1_1 [1:0] $end
$var reg 2 I s1_2 [1:0] $end
$upscope $end
$upscope $end
$upscope $end
$enddefinitions $end
#0
$dumpvars
b0 I
b11 H
b10 G
b1 F
b1 E
b1110 D
b111111111 C
b1111 B
b1111 A
b1111111011 @
b1111111 ?
b11110111 >
b11100001 =
b11111101 <
b1000 ;
b1000 :
b111 9
b1 8
b1110 7
b1100110 6
b11111111 5
b10000010 4
b11111111 3
b10011001 2
b0 1
b100 0
b0 /
b0 .
b0 -
b0 ,
b10011001 +
b0 *
b1000 )
b100 (
b0 '
1&
b0 %
b1000 $
b100 #
0"
b0 !
$end
#1
1"
#2
0"
#3
1"
#4
0"
#5
b10110111 +
b10110111 2
b1001000 6
b10000010 =
b1000 D
b101 8
b1001 :
b1 I
b1101011 <
b10100 4
b10 E
b1101 7
b1101 9
b1 H
b11 F
b11100 ;
b11101011 3
b1101 B
b11111101 5
b111110111 C
b10011001 !
b10011001 '
b1000 ,
b1000 1
b10011001 /
1"
0&
#6
0"
#7
b1100111 +
b1100111 2
b10011000 6
b11010 =
b1 D
b0 8
b0 :
b0 I
b0 G
b101010 <
b1010101 4
b1010 E
b100 7
b1 9
b0 F
b1110101 ;
b10000010 3
b1110 A
b1 B
b11100001 5
b101100110 C
b10110111 !
b10110111 '
b10011001 ,
b10011001 1
b10110111 /
1"
#8
0"
#9
b1011101 +
b1011101 2
b10100010 6
b110001 =
b11 D
b1 8
b1000 :
b10 G
b11111101 <
b10000010 4
b1 E
b1001 7
b1100 9
b0 H
b11 F
b11100011 ;
b10100 3
b1000 A
b10 B
b10000010 5
b101001000 C
b1100111 !
b1100111 '
b10110111 ,
b10110111 1
b1100111 /
1"
#10
0"
#11
b11111010 +
b11111010 2
b101 6
b1000100 =
b100 D
b1110 8
b111 :
b11 I
b1 G
b1010111 <
b101000 4
b100 E
b101 7
b1001 9
b1 H
b10 F
b10100010 ;
b1010101 3
b1 A
b1010 B
b11010 5
b110011000 C
b1011101 !
b1011101 '
b1100111 ,
b1100111 1
b1011101 /
1"
#12
0"
#13
b10100 +
b10100 2
b11101011 6
b10110111 =
b1011 D
b1010 8
b110 :
b10 I
b11000001 <
b10111110 4
b111 E
b100 7
b1 9
b0 F
b1110101 ;
b10000010 3
b11 A
b1 B
b110001 5
b110100010 C
b11111010 !
b11111010 '
b1011101 ,
b1011101 1
b11111010 /
1"
#14
0"
#15
b10011001 +
b10011001 2
b0 !
b0 '
b1100110 6
b11100001 =
b1110 D
b1 8
b1000 :
b0 I
b10 G
b11111101 <
b10000010 4
b1 E
b1110 7
b111 9
b11 H
b1 F
b1000 ;
b11111111 3
b1111 A
b1111 B
b11111111 5
b111111111 C
b0 /
b0 ,
b0 1
1"
1&
#16
0"
b10000 $
b10000 )
#17
1"
#18
0"
#19
b111110 +
b111110 2
b11000001 6
b10010100 =
b1001 D
b1110 8
b111 :
b11 I
b1 G
b1010111 <
b101000 4
b100 E
b1011 7
b1110 9
b10 H
b11 F
b1001001 ;
b10111110 3
b111 B
b11110111 5
b111101111 C
b10011001 !
b10011001 '
b10000 ,
b10000 1
b10011001 /
1"
0&
#20
0"
#21
b1100111 +
b1100111 2
b10011000 6
b11010 =
b1 D
b0 8
b0 :
b0 I
b0 G
b101010 <
b1010101 4
b1010 E
b100 7
b1 9
b1 H
b0 F
b1110101 ;
b10000010 3
b1110 A
b1 B
b11100001 5
b101100110 C
b111110 !
b111110 '
b10011001 ,
b10011001 1
b111110 /
1"
#22
0"
#23
b110010 +
b110010 2
b11001101 6
b11010110 =
b1101 D
b1001 8
b1100 :
b11 G
b1000011 <
b111100 4
b110 E
b1111 7
b1111 9
b11 H
b11 F
b11011111 ;
b101000 3
b1001 A
b100 B
b10010100 5
b111000001 C
b1100111 !
b1100111 '
b111110 ,
b111110 1
b1100111 /
1"
#24
0"
#25
b11111010 +
b11111010 2
b101 6
b1000100 =
b100 D
b1110 8
b111 :
b11 I
b1 G
b1010111 <
b101000 4
b100 E
b101 7
b1001 9
b1 H
b10 F
b10100010 ;
b1010101 3
b1 A
b1010 B
b11010 5
b110011000 C
b110010 !
b110010 '
b1100111 ,
b1100111 1
b110010 /
1"
#26
0"
#27
b1011001 +
b1011001 2
b10100110 6
b1110001 =
b111 D
b1 8
b1000 :
b0 I
b10 G
b11111101 <
b10000010 4
b1 E
b1100 7
b101 9
b1 F
b11001011 ;
b111100 3
b1101 A
b110 B
b11010110 5
b111001101 C
b11111010 !
b11111010 '
b110010 ,
b110010 1
b11111010 /
1"
#28
0"
#29
b1000101 +
b1000101 2
b10111010 6
b111011 =
b11 D
b111 8
b1011 :
b11 I
b10101000 <
b11010111 4
b1011 E
b1111 7
b1111 9
b11 H
b11 F
b11011111 ;
b101000 3
b100 A
b100 B
b1000100 5
b100000101 C
b1011001 !
b1011001 '
b11111010 ,
b11111010 1
b1011001 /
1"
#30
0"
#31
b10010101 +
b10010101 2
b1101010 6
b10100011 =
b1010 D
b1011 8
b1110 :
b10 I
b11 G
b11101001 <
b10010110 4
b11 E
b100 7
b1 9
b1 H
b0 F
b1110101 ;
b10000010 3
b111 A
b1 B
b1110001 5
b110100110 C
b1000101 !
b1000101 '
b1011001 ,
b1011001 1
b1000101 /
1"
#32
0"
#33
b11110101 +
b11110101 2
b1010 6
b11 =
b0 D
b0 7
b0 9
b0 H
b100000 ;
b11010111 3
b11 A
b1011 B
b111011 5
b110111010 C
b10010101 !
b10010101 '
b1000101 ,
b1000101 1
b10010101 /
1"
#34
0"
#35
b1001 +
b1001 2
b11110110 6
b11111001 =
b1111 D
b1100 8
b101 :
b1 I
b1 G
b10111100 <
b11000011 4
b1001 E
b11 7
b1010 9
b10 H
b10 F
b1100001 ;
b10010110 3
b1010 A
b11 B
b10100011 5
b101101010 C
b11110101 !
b11110101 '
b10010101 ,
b10010101 1
b11110101 /
1"
#36
0"
#37
b10110101 +
b10110101 2
b1001010 6
b10000011 =
b1000 D
b1011 8
b1110 :
b10 I
b11 G
b11101001 <
b10010110 4
b11 E
b0 A
b11 5
b100001010 C
b1001 !
b1001 '
b11110101 ,
b11110101 1
b1001 /
1"
#38
0"
#39
b10011001 +
b10011001 2
b0 !
b0 '
b1100110 6
b11100001 =
b1110 D
b1 8
b1000 :
b0 I
b10 G
b11111101 <
b10000010 4
b1 E
b1110 7
b111 9
b11 H
b1 F
b1000 ;
b11111111 3
b1111 A
b1111 B
b11111111 5
b111111111 C
b0 /
b0 ,
b0 1
1"
1&
